InlinePlaylink/__init__.py
InlinePlaylink/custom_exception.py
InlinePlaylink/logger.py
InlinePlaylink/youtube.py
inlineplaylink-0.0.2.dist-info/LICENSE
inlineplaylink-0.0.2.dist-info/METADATA
inlineplaylink-0.0.2.dist-info/WHEEL
inlineplaylink-0.0.2.dist-info/top_level.txt
inlineplaylink-0.0.2.dist-info/RECORD
